powershift/__init__.py
powershift/cluster/__init__.py
powershift_cluster-1.0.3.dist-info/DESCRIPTION.rst
powershift_cluster-1.0.3.dist-info/METADATA
powershift_cluster-1.0.3.dist-info/RECORD
powershift_cluster-1.0.3.dist-info/WHEEL
powershift_cluster-1.0.3.dist-info/entry_points.txt
powershift_cluster-1.0.3.dist-info/metadata.json
powershift_cluster-1.0.3.dist-info/top_level.txt
