Metadata-Version: 2.0
Name: powershift-cluster
Version: 1.0.3
Summary: PowerShift command plugin for creating OpenShift clusters.
Home-page: https://github.com/getwarped/powershift-cli-cluster
Author: Graham Dumpleton
Author-email: Graham.Dumpleton@gmail.com
License: BSD
Keywords: openshift kubernetes
Platform: UNKNOWN
Classifier: Development Status :: 4 - Beta
Classifier: License :: OSI Approved :: BSD License
Classifier: Programming Language :: Python :: 3
Classifier: Programming Language :: Python :: 3.5
Requires-Dist: powershift (>=1.3.7)
